Librarymu/__init__.py
Librarymu/my_class.py
lingkar33423308/__init__.py
lingkar33423308/lingkaran.py
luaslingkar33423308-4.0.dist-info/METADATA
luaslingkar33423308-4.0.dist-info/WHEEL
luaslingkar33423308-4.0.dist-info/top_level.txt
luaslingkar33423308-4.0.dist-info/RECORD
