Metadata-Version: 2.1
Name: luaslingkar33423308
Version: 4.0
Summary: Simple library to calculate golden ratio
Author: Aliza
Author-email: <faizata00@gmail.com>
License: MIT
Keywords: luas_lingkaran,luaslingkaran
Classifier: Development Status :: 1 - Planning
